[
  {
    "ContainingType": "AuthController",
    "Method": "Login",
    "RelativePath": "api/auth/login",
    "HttpMethod": "POST",
    "IsController": true,
    "Order": 0,
    "Parameters": [
      {
        "Name": "loginRequest",
        "Type": "LoginRequest",
        "IsRequired": true
      }
    ],
    "ReturnTypes": []
  },
  {
    "ContainingType": "AuthController",
    "Method": "RefreshToken",
    "RelativePath": "api/auth/refresh-token",
    "HttpMethod": "POST",
    "IsController": true,
    "Order": 0,
    "Parameters": [
      {
        "Name": "token",
        "Type": "System.String",
        "IsRequired": false
      }
    ],
    "ReturnTypes": []
  },
  {
    "ContainingType": "TaskFlow_API.Controllers.TarefaController",
    "Method": "AddTarefa",
    "RelativePath": "api/tarefa",
    "HttpMethod": "POST",
    "IsController": true,
    "Order": 0,
    "Parameters": [
      {
        "Name": "tarefa",
        "Type": "TaskFlow_API.Domains.Tarefa",
        "IsRequired": true
      }
    ],
    "ReturnTypes": [
      {
        "Type": "TaskFlow_API.Shared.Response\u00601[[TaskFlow_API.Domains.Tarefa, TaskFlow-API, Version=1.0.0.0, Culture=neutral, PublicKeyToken=null]]",
        "MediaTypes": [
          "text/plain",
          "application/json",
          "text/json"
        ],
        "StatusCode": 200
      }
    ]
  },
  {
    "ContainingType": "TaskFlow_API.Controllers.TarefaController",
    "Method": "UpdateTarefa",
    "RelativePath": "api/tarefa",
    "HttpMethod": "PUT",
    "IsController": true,
    "Order": 0,
    "Parameters": [
      {
        "Name": "tarefa",
        "Type": "TaskFlow_API.Domains.Tarefa",
        "IsRequired": true
      }
    ],
    "ReturnTypes": [
      {
        "Type": "TaskFlow_API.Shared.Response\u00601[[TaskFlow_API.Domains.Tarefa, TaskFlow-API, Version=1.0.0.0, Culture=neutral, PublicKeyToken=null]]",
        "MediaTypes": [
          "text/plain",
          "application/json",
          "text/json"
        ],
        "StatusCode": 200
      }
    ]
  },
  {
    "ContainingType": "TaskFlow_API.Controllers.TarefaController",
    "Method": "GetAllTarefas",
    "RelativePath": "api/tarefa",
    "HttpMethod": "GET",
    "IsController": true,
    "Order": 0,
    "Parameters": [],
    "ReturnTypes": [
      {
        "Type": "System.Collections.Generic.IEnumerable\u00601[[TaskFlow_API.Domains.Tarefa, TaskFlow-API, Version=1.0.0.0, Culture=neutral, PublicKeyToken=null]]",
        "MediaTypes": [
          "text/plain",
          "application/json",
          "text/json"
        ],
        "StatusCode": 200
      }
    ]
  },
  {
    "ContainingType": "TaskFlow_API.Controllers.TarefaController",
    "Method": "GetTarefaById",
    "RelativePath": "api/tarefa/{id}",
    "HttpMethod": "GET",
    "IsController": true,
    "Order": 0,
    "Parameters": [
      {
        "Name": "id",
        "Type": "System.Guid",
        "IsRequired": true
      }
    ],
    "ReturnTypes": [
      {
        "Type": "TaskFlow_API.Shared.Response\u00601[[TaskFlow_API.Domains.Tarefa, TaskFlow-API, Version=1.0.0.0, Culture=neutral, PublicKeyToken=null]]",
        "MediaTypes": [
          "text/plain",
          "application/json",
          "text/json"
        ],
        "StatusCode": 200
      }
    ]
  },
  {
    "ContainingType": "TaskFlow_API.Controllers.TarefaController",
    "Method": "DeleteTarefa",
    "RelativePath": "api/tarefa/{id}",
    "HttpMethod": "DELETE",
    "IsController": true,
    "Order": 0,
    "Parameters": [
      {
        "Name": "id",
        "Type": "System.Guid",
        "IsRequired": true
      }
    ],
    "ReturnTypes": [
      {
        "Type": "TaskFlow_API.Shared.Response\u00601[[TaskFlow_API.Domains.Tarefa, TaskFlow-API, Version=1.0.0.0, Culture=neutral, PublicKeyToken=null]]",
        "MediaTypes": [
          "text/plain",
          "application/json",
          "text/json"
        ],
        "StatusCode": 200
      }
    ]
  },
  {
    "ContainingType": "TaskFlow_API.Controllers.TarefaController",
    "Method": "GetPagination",
    "RelativePath": "api/tarefa/pagination",
    "HttpMethod": "POST",
    "IsController": true,
    "Order": 0,
    "Parameters": [
      {
        "Name": "pageEvent",
        "Type": "TaskFlow_API.Domains.PageEvent",
        "IsRequired": true
      }
    ],
    "ReturnTypes": [
      {
        "Type": "TaskFlow_API.Shared.ResponsePagination",
        "MediaTypes": [
          "text/plain",
          "application/json",
          "text/json"
        ],
        "StatusCode": 200
      }
    ]
  },
  {
    "ContainingType": "TaskFlow_API.Controllers.TarefaController",
    "Method": "ChangeStatusTarefa",
    "RelativePath": "api/tarefa/status/{id}",
    "HttpMethod": "PATCH",
    "IsController": true,
    "Order": 0,
    "Parameters": [
      {
        "Name": "id",
        "Type": "System.Guid",
        "IsRequired": true
      },
      {
        "Name": "concluido",
        "Type": "System.Boolean",
        "IsRequired": true
      }
    ],
    "ReturnTypes": [
      {
        "Type": "TaskFlow_API.Shared.Response\u00601[[TaskFlow_API.Domains.Tarefa, TaskFlow-API, Version=1.0.0.0, Culture=neutral, PublicKeyToken=null]]",
        "MediaTypes": [
          "text/plain",
          "application/json",
          "text/json"
        ],
        "StatusCode": 200
      }
    ]
  },
  {
    "ContainingType": "TaskFlow_API.Controllers.UsuarioController",
    "Method": "AddUsuario",
    "RelativePath": "api/usuario",
    "HttpMethod": "POST",
    "IsController": true,
    "Order": 0,
    "Parameters": [
      {
        "Name": "usuario",
        "Type": "TaskFlow_API.Domains.Usuario",
        "IsRequired": true
      }
    ],
    "ReturnTypes": [
      {
        "Type": "TaskFlow_API.Shared.Response\u00601[[TaskFlow_API.Domains.Usuario, TaskFlow-API, Version=1.0.0.0, Culture=neutral, PublicKeyToken=null]]",
        "MediaTypes": [
          "text/plain",
          "application/json",
          "text/json"
        ],
        "StatusCode": 200
      }
    ]
  },
  {
    "ContainingType": "TaskFlow_API.Controllers.UsuarioController",
    "Method": "UpdatePasswordUsuario",
    "RelativePath": "api/usuario",
    "HttpMethod": "PATCH",
    "IsController": true,
    "Order": 0,
    "Parameters": [
      {
        "Name": "email",
        "Type": "System.String",
        "IsRequired": false
      },
      {
        "Name": "senhaAtual",
        "Type": "System.String",
        "IsRequired": false
      },
      {
        "Name": "senhaNova",
        "Type": "System.String",
        "IsRequired": false
      }
    ],
    "ReturnTypes": [
      {
        "Type": "TaskFlow_API.Shared.Response\u00601[[TaskFlow_API.Domains.Usuario, TaskFlow-API, Version=1.0.0.0, Culture=neutral, PublicKeyToken=null]]",
        "MediaTypes": [
          "text/plain",
          "application/json",
          "text/json"
        ],
        "StatusCode": 200
      }
    ]
  },
  {
    "ContainingType": "TaskFlow_API.Controllers.UsuarioController",
    "Method": "GetUsuarioById",
    "RelativePath": "api/usuario/{id}",
    "HttpMethod": "GET",
    "IsController": true,
    "Order": 0,
    "Parameters": [
      {
        "Name": "id",
        "Type": "System.Guid",
        "IsRequired": true
      }
    ],
    "ReturnTypes": [
      {
        "Type": "TaskFlow_API.Shared.Response\u00601[[TaskFlow_API.Domains.Usuario, TaskFlow-API, Version=1.0.0.0, Culture=neutral, PublicKeyToken=null]]",
        "MediaTypes": [
          "text/plain",
          "application/json",
          "text/json"
        ],
        "StatusCode": 200
      }
    ]
  },
  {
    "ContainingType": "TaskFlow_API.Controllers.UsuarioController",
    "Method": "GetUsuarioByEmail",
    "RelativePath": "api/usuario/email",
    "HttpMethod": "GET",
    "IsController": true,
    "Order": 0,
    "Parameters": [
      {
        "Name": "email",
        "Type": "System.String",
        "IsRequired": false
      }
    ],
    "ReturnTypes": [
      {
        "Type": "TaskFlow_API.Shared.Response\u00601[[TaskFlow_API.Domains.Usuario, TaskFlow-API, Version=1.0.0.0, Culture=neutral, PublicKeyToken=null]]",
        "MediaTypes": [
          "text/plain",
          "application/json",
          "text/json"
        ],
        "StatusCode": 200
      }
    ]
  }
]